fireball/__init__.py
fireball-25.1.0.dist-info/licenses/LICENSE
fireball-25.1.0.dist-info/METADATA
fireball-25.1.0.dist-info/WHEEL
fireball-25.1.0.dist-info/entry_points.txt
fireball-25.1.0.dist-info/top_level.txt
fireball-25.1.0.dist-info/RECORD
