Metadata-Version: 2.4
Name: fireball
Version: 25.1.0
Summary: Add your description here
Requires-Python: >=3.8
License-File: LICENSE
Requires-Dist: pyinstrument
Requires-Dist: typer
Dynamic: license-file
